dualsense_controller/__init__.py
dualsense_controller/api/DualSenseController.py
dualsense_controller/api/Properties.py
dualsense_controller/api/__init__.py
dualsense_controller/api/contextmanager.py
dualsense_controller/api/enum.py
dualsense_controller/api/property/AccelerometerProperty.py
dualsense_controller/api/property/BatteryProperty.py
dualsense_controller/api/property/BenchmarkProperty.py
dualsense_controller/api/property/ButtonProperty.py
dualsense_controller/api/property/ConnectionProperty.py
dualsense_controller/api/property/ExceptionProperty.py
dualsense_controller/api/property/GyroscopeProperty.py
dualsense_controller/api/property/JoyStickProperty.py
dualsense_controller/api/property/LightbarProperty.py
dualsense_controller/api/property/MicrophoneProperty.py
dualsense_controller/api/property/OrientationProperty.py
dualsense_controller/api/property/PlayerLedsProperty.py
dualsense_controller/api/property/RumbleProperty.py
dualsense_controller/api/property/TouchFingerProperty.py
dualsense_controller/api/property/TriggerEffectProperty.py
dualsense_controller/api/property/TriggerFeedbackProperty.py
dualsense_controller/api/property/TriggerProperty.py
dualsense_controller/api/property/__init__.py
dualsense_controller/api/property/base.py
dualsense_controller/api/typedef.py
dualsense_controller/core/Benchmarker.py
dualsense_controller/core/DualSenseControllerCore.py
dualsense_controller/core/HidControllerDevice.py
dualsense_controller/core/__init__.py
dualsense_controller/core/core/Lockable.py
dualsense_controller/core/core/__init__.py
dualsense_controller/core/enum.py
dualsense_controller/core/exception.py
dualsense_controller/core/hidapi/LICENSE.txt
dualsense_controller/core/hidapi/__init__.py
dualsense_controller/core/hidapi/hidapi.py
dualsense_controller/core/log.py
dualsense_controller/core/report/__init__.py
dualsense_controller/core/report/in_report/Bt01InReport.py
dualsense_controller/core/report/in_report/Bt31InReport.py
dualsense_controller-0.3.1.dist-info/LICENSE
dualsense_controller-0.3.1.dist-info/METADATA
dualsense_controller-0.3.1.dist-info/WHEEL
dualsense_controller-0.3.1.dist-info/entry_points.txt
dualsense_controller-0.3.1.dist-info/RECORD
