Metadata-Version: 2.1
Name: dualsense-controller
Version: 0.3.1
Summary: Use DualSense Controller with Python.
Home-page: https://github.com/yesbotics/dualsense-controller-python
License: MIT
Keywords: DualSense Controller,PS5,PlayStation 5,Game Controller,Gaming,Robotics
Author: Albrecht Nitsche
Author-email: albrechtnitsche@gmail.com
Requires-Python: >=3.10,<4.0
Classifier: License :: OSI Approved :: MIT License
Classifier: Operating System :: Microsoft :: Windows
Classifier: Operating System :: POSIX :: Linux
Classifier: Programming Language :: Python :: 3
Classifier: Programming Language :: Python :: 3.10
Classifier: Programming Language :: Python :: 3.11
Classifier: Programming Language :: Python :: 3.12
Classifier: Topic :: System :: Hardware :: Universal Serial Bus (USB) :: Human Interface Device (HID)
Classifier: Topic :: System :: Hardware :: Universal Serial Bus (USB) :: Wireless Controller
Requires-Dist: cffi (>=1.15.1,<2.0.0)
Requires-Dist: deprecated (>=1.2.14,<2.0.0)
Requires-Dist: pyee (>=11.0.0,<12.0.0)
Project-URL: Repository, https://github.com/yesbotics/dualsense-controller-python
